treecraft/__init__.py
treecraft/__main__.py
treecraft/cli.py
treecraft/core/__init__.py
treecraft/core/generator.py
treecraft/core/parser.py
treecraft/utils/__init__.py
treecraft/utils/helpers.py
treecraft-0.1.1.dist-info/LICENSE
treecraft-0.1.1.dist-info/METADATA
treecraft-0.1.1.dist-info/WHEEL
treecraft-0.1.1.dist-info/entry_points.txt
treecraft-0.1.1.dist-info/top_level.txt
treecraft-0.1.1.dist-info/RECORD
