Metadata-Version: 2.1
Name: treecraft
Version: 0.1.1
Summary: Generate directory structures from text-based tree representations
Author-email: Ashwin Murali <ashwinmurali27@gmail.com>
License: MIT
Project-URL: Homepage, https://github.com/ashwin271/treecraft
Project-URL: Repository, https://github.com/ashwin271/treecraft
Classifier: Development Status :: 3 - Alpha
Classifier: Intended Audience :: Developers
Classifier: License :: OSI Approved :: MIT License
Classifier: Operating System :: OS Independent
Classifier: Programming Language :: Python :: 3
Classifier: Programming Language :: Python :: 3.7
Classifier: Programming Language :: Python :: 3.8
Classifier: Programming Language :: Python :: 3.9
Requires-Python: >=3.7
License-File: LICENSE
